watchsql/__init__.py
watchsql/__main__.py
watchsql/main.py
watchsql/screen.py
watchsql/sql.py
watchsql/watchsql_orig.py
watchsql-1.2.9.dist-info/LICENSE
watchsql-1.2.9.dist-info/METADATA
watchsql-1.2.9.dist-info/WHEEL
watchsql-1.2.9.dist-info/entry_points.txt
watchsql-1.2.9.dist-info/top_level.txt
watchsql-1.2.9.dist-info/RECORD
