Metadata-Version: 2.1
Name: watchsql
Version: 1.2.9
Summary: Comand-line utility to monitor the response of a SQL query
Author: jakobst1n
License: GNU GENERAL PUBLIC LICENSE
Project-URL: Homepage, https://github.com/jakobst1n/watchsql
Classifier: Programming Language :: Python
Classifier: Programming Language :: Python :: 3
Requires-Python: >=3.9
License-File: LICENSE
Requires-Dist: cusser ==0.1.1
Requires-Dist: mysqlclient ==2.0.2
Requires-Dist: numpy ==1.26.0
Requires-Dist: ochre ==0.1.1
Requires-Dist: plotille ==4.0.2
Requires-Dist: six ==1.16.0
Requires-Dist: stransi ==0.1.0
Provides-Extra: dev
Requires-Dist: black ; extra == 'dev'
Requires-Dist: bumpver ; extra == 'dev'
Requires-Dist: isort ; extra == 'dev'
Requires-Dist: pip-tools ; extra == 'dev'
Requires-Dist: pytest ; extra == 'dev'
